ionoscloud_container_registry/__init__.py
ionoscloud_container_registry/api_client.py
ionoscloud_container_registry/api_response.py
ionoscloud_container_registry/configuration.py
ionoscloud_container_registry/exceptions.py
ionoscloud_container_registry/rest.py
ionoscloud_container_registry/test-driver.py
ionoscloud_container_registry/api/__init__.py
ionoscloud_container_registry/api/artifacts_api.py
ionoscloud_container_registry/api/locations_api.py
ionoscloud_container_registry/api/names_api.py
ionoscloud_container_registry/api/registries_api.py
ionoscloud_container_registry/api/repositories_api.py
ionoscloud_container_registry/api/tokens_api.py
ionoscloud_container_registry/api/vulnerabilities_api.py
ionoscloud_container_registry/models/__init__.py
ionoscloud_container_registry/models/api_error_message.py
ionoscloud_container_registry/models/api_error_response.py
ionoscloud_container_registry/models/api_resource_metadata.py
ionoscloud_container_registry/models/artifact.py
ionoscloud_container_registry/models/artifact_metadata.py
ionoscloud_container_registry/models/artifact_metadata_all_of.py
ionoscloud_container_registry/models/artifact_read.py
ionoscloud_container_registry/models/artifact_read_list.py
ionoscloud_container_registry/models/artifact_vulnerability_read_list.py
ionoscloud_container_registry/models/credentials.py
ionoscloud_container_registry/models/day.py
ionoscloud_container_registry/models/error.py
ionoscloud_container_registry/models/error_messages.py
ionoscloud_container_registry/models/feature.py
ionoscloud_container_registry/models/feature_vulnerability_scanning.py
ionoscloud_container_registry/models/links.py
ionoscloud_container_registry/models/location.py
ionoscloud_container_registry/models/locations_response.py
ionoscloud_container_registry/models/metadata.py
ionoscloud_container_registry/models/pagination.py
ionoscloud_container_registry/models/pagination_links.py
ionoscloud_container_registry/models/patch_registry_input.py
ionoscloud_container_registry-1.1.0.dist-info/LICENSE
ionoscloud_container_registry-1.1.0.dist-info/METADATA
ionoscloud_container_registry-1.1.0.dist-info/WHEEL
ionoscloud_container_registry-1.1.0.dist-info/top_level.txt
ionoscloud_container_registry-1.1.0.dist-info/RECORD
